gxctmm/__init__.py
gxctmm/fit.py
gxctmm/log.py
gxctmm/plot.py
gxctmm/preprocess.py
gxctmm/reml.R
gxctmm/skeleton.py
gxctmm/util.py
gxctmm/wald.py
gxctmm-0.3.0.dist-info/LICENSE.txt
gxctmm-0.3.0.dist-info/METADATA
gxctmm-0.3.0.dist-info/WHEEL
gxctmm-0.3.0.dist-info/top_level.txt
gxctmm-0.3.0.dist-info/RECORD
